anyapi_creator/__init__.py
anyapi_creator/anyapi.py
anyapi_creator-0.1.0.dist-info/METADATA
anyapi_creator-0.1.0.dist-info/WHEEL
anyapi_creator-0.1.0.dist-info/top_level.txt
anyapi_creator-0.1.0.dist-info/RECORD
