Metadata-Version: 2.4
Name: anyapi_creator
Version: 0.1.0
Summary: Python client for AnyAPI Creator
Author: Preet Vaishnav
License: MIT
Requires-Python: >=3.7
Requires-Dist: aiohttp
